[{"__symbolic":"module","version":4,"metadata":{"LoadingIndicatorComponent":{"__symbolic":"class","decorators":[{"__symbolic":"call","expression":{"__symbolic":"reference","module":"@angular/core","name":"Component","line":2,"character":1},"arguments":[{"selector":"rd-loading-indicator","template":"\n    <img [src]=\"src\" [height]=\"height\" [width]=\"width\" style=\"margin: auto !important;\" />\n  ","styles":["\n    :host {\n        display: inline-block;\n        background-color: black;\n    }\n  "]}]}],"members":{"height":[{"__symbolic":"property","decorators":[{"__symbolic":"call","expression":{"__symbolic":"reference","module":"@angular/core","name":"Input","line":15,"character":3}}]}],"width":[{"__symbolic":"property","decorators":[{"__symbolic":"call","expression":{"__symbolic":"reference","module":"@angular/core","name":"Input","line":16,"character":3}}]}],"src":[{"__symbolic":"property","decorators":[{"__symbolic":"call","expression":{"__symbolic":"reference","module":"@angular/core","name":"Input","line":17,"character":3}}]}],"__ctor__":[{"__symbolic":"constructor"}],"ngOnInit":[{"__symbolic":"method"}],"ngOnDestroy":[{"__symbolic":"method"}]}}}}]